weekdatemac/__init__.py
weekdatemac/week_menu_bar.py
weekdatemac-1.0.1.dist-info/LICENSE
weekdatemac-1.0.1.dist-info/METADATA
weekdatemac-1.0.1.dist-info/WHEEL
weekdatemac-1.0.1.dist-info/top_level.txt
weekdatemac-1.0.1.dist-info/RECORD
