Metadata-Version: 2.1
Name: weekdatemac
Version: 1.0.1
Summary: A macOS script to display the current week number in the menu bar.
Home-page: https://github.com/Silicon27/weekdatemac
Author: Yang Silicon
Author-email: yangsiliconl@gmail.com
License: UNKNOWN
Platform: UNKNOWN
Classifier: Programming Language :: Python :: 3
Classifier: License :: OSI Approved :: MIT License
Classifier: Operating System :: OS Independent
